Metadata-Version: 1.1
Name: BigQuery-Python
Version: 1.13.0
Summary: Simple Python client for interacting with Google BigQuery.
Home-page: https://github.com/tylertreat/BigQuery-Python
Author: Tyler Treat
Author-email: ttreat31@gmail.com
License: Apache
Platform: UNKNOWN
Classifier: Development Status :: 5 - Production/Stable
Classifier: Environment :: Web Environment
Classifier: Intended Audience :: Developers
Classifier: Operating System :: OS Independent
Classifier: Programming Language :: Python
